catboys/__init__.py
catboys/catboys.py
catboys/dict.py
catboys/errors.py
catboys/http.py
catboys-1.0.6.dist-info/LICENSE
catboys-1.0.6.dist-info/METADATA
catboys-1.0.6.dist-info/WHEEL
catboys-1.0.6.dist-info/top_level.txt
catboys-1.0.6.dist-info/RECORD
