Metadata-Version: 2.1
Name: catboys
Version: 1.0.6
Summary: A Python module that uses the Catboys API
Home-page: https://github.com/Catboys-Dev/catboys-py
Author: Kristian Kramer
Author-email: hello@kk.dev
License: GNU v3
License-File: LICENSE
Requires-Dist: requests
